{
	
"keysForContent":{
	
	"title":"கிரெடிட்அக்சஸ் கிராமின் லிமிடெட்",
	"applicationName":"முக்கிய உண்மைகள் அறிக்கை",
	"subHeading":"(வட்டி விகிதம் மற்றும் கட்டணம்/கட்டணங்கள்)",

		"customerName":" வாடிக்கையாளரின் பெயர்:",
		"customerId":"வாடிக்கையாளர் ஐடி:",
		"kendraName":"மையம் பெயர்:",
		"kendraId":"மையம் ஐடி:",
		"loanAccountNumber":"கடன் கணக்கு எண்:",
		"typeOfLoan":"கடனின் வகை:",
		"sanctionLoanAmount":"ஒப்புதல் அளிக்கப்பட்ட கடன் தொகை (ரூபாயில்) ",
		"disbursementSchedule":"விநியோக அட்டவணை",
			"disbursementSchedule1":"i). பல தவணைகளாக விநியோகித்தல் அல்லது ஒரே தவணையில் 100%   விநியோகித்தல்.",
			"disbursementSchedule2":"ii).  பல தவணைகளாக விநியோகிக்கப்பட்டால், அது தொடர்பான விவரங்கள் இருக்கும் கடன் ஒப்பந்தத்தின் பிரிவைக் குறிப்பிடவும்",
		"loanTerm":"கடன் காலம் (ஆண்டு/மாதம்/நாட்கள்)",
		"months":"Month",
		"installmentDetails":"தவணை விவரங்கள்:",
			
			"instalmentType":"தவணைகளின் வகை ",
			"EPIsNos":"இபிஐ  -களின் எண்ணிக்கை ",
			"EPI":"இபிஐ (ரூ)",
			"CommencementOfRepaymentPostSanction":"கடன் வழங்கப்பட்ட பிறகு திரும்பச் செலுத்துதல்",
		
		"InterestRate&Type":"வட்டி விகிதம் (%) மற்றும் வகை (நிலையானது அல்லது மாறக்கூடியது அல்லது இரண்டும் கலந்தது",
	    "AdditionalInformation":"மாறக்கூடிய வட்டி விகிதம் எனில் கூடுதல் தகவல்கள்",

			"ReferenceBenchmark":"குறிப்புத் தரநிலை",
			"BenchmarkRate":"பெஞ்ச்மார்க் விகிதம்(%)(பி)",
			"Spread":"பரவல்(%) ( எஸ் )",
		    "FinalRate":"இறுதி விகிதம் (%)ஆர்=(பி)+(எஸ்)",
			"RestPeriodicity":"வட்டி கணக்கீட்டு இடைக்காலம் (மாதம்)",
			"B":"பி",
			"S":"எஸ்",
			"ChangeImpact":"குறிப்புத் தரநிலை மாற்றங்களின் தாக்கம் பின்வருபவற்றில் ‘R’ -இல் 25bps மாற்றம் ",
			

		"FeeOrCharges":"கட்டணம்/கட்டணங்கள்",
			 
				"PayableToTheRE(A)":"  ஆர்.இ (ஏ) -க்கு செலுத்த வேண்டியது ",
				"OneTimeOrRecurring1":"ஒரு முறை / தொடர் முறை ",
				"Amount":"தொகை (ரூ) அல்லது சதவீதத்தில்  (%) பொருந்தும் வகையில் ",
				"PayableToTheRE(B)":"ஆர்.இ (பி) மூலமாக மூன்றாம் தரப்பினருக்கு செலுத்த வேண்டியது ",
				"OneTimeOrRecurring2":"ஒரு முறை / தொடர் முறை",
				"AmountInRs":"தொகை (ரூ) அல்லது சதவீதத்தில்  (%) பொருந்தும் வகையில்",

			"ProcessingFees":"செயலாக்க கட்டணம்",
			"InsuranceCharges":"காப்பீட்டுக் கட்டணம் ",
			"Valuation Fees":"மதிப்பீட்டுக் கட்டணங்கள் ",
			"otherLegalCharges":"இதரவை (குறிப்பிடவும் ) சட்டம் தொடர்பான கட்டணங்கள் ",

		"AnnualPercentageRate":"ஆண்டு சதவீத விகிதம் (ஏபிஆர்)(%)",
		"ContingentCharges":"எதிர்பாரா கட்டண விவரங்கள் (ரூபாயில் அல்லது சதவீதத்தில் (%), பொருந்தும் வகையில்)",

				"PenalCharges":"தாமதமாக செலுத்துவதற்கான அபராத கட்டணங்கள், ஏதேனும் இருந்தால்.",
				"otherPenalCharges":"பிற  அபராத கட்டணங்கள்,  ஏதேனும் இருந்தால். ",
				"ForeclosureCharges":"முன் முடித்தல் கட்டணங்கள்,  ஏதேனும் இருந்தால். ",
				"SwitchingLoanCharges":"கடன் திட்டத்தை மாறக்கூடிய வட்டி விகிதத்திலிருந்து நிலையான வட்டி விகிதத்திற்கு மாற்றுதல் மற்றும் இதற்கு நேர்மாறாக மாற்றியமைப்பதற்கான கட்டணங்கள்.",
				"AnyOtherCharges":"ஏதேனும் பிற கட்டணங்கள் (குறிப்பிடவும்) ",

	"OtherQualitativeInformation":"<br>மற்ற பயனுள்ள தகவல்கள்",

			"ClauseOfLoanAgreementRelatingToEngagementOfRecoveryAgent":"மீட்பு முகவர்களை அமர்த்தல் தொடர்பான கடன் ஒப்பந்தத்தின் உட்பிரிவு. ",
			"ClauseOfLoanAgreementwhichDetailsGrievanceRedressalMechanism":"குறைதீர் செயல்முறைகளின் விவரங்களை குறிப்பிடும்  கடன் ஒப்பந்தத்தின் உட்பிரிவு.",
			"RedressalMechanismValue":"Clause 23",
			"phoneNum":"நோடல் குறைதீர் அதிகாரியின் தொலைபேசி எண் மற்றும் மின்னஞ்சல் முகவரி ஐ.டி ",
			"securitization(Yes/NO)":"இந்த கடன் இப்போது அல்லது எதிர்காலத்தில் பிற  ஆர்.இ  -களுக்கு மாற்றப்படுதலுக்கு அல்லது பத்திரமாக்கப்படுதலுக்கு உட்படுத்தப்படுமா? (ஆம்/இல்லை)",
			"lendingArrangementDetailsMaybeFurnished":"கூட்டு கடன் வழங்கப்படுவதாக இருந்தால் (உதாரணமாக, இணை கடன் வழங்குவது / வெளியிட ஏற்பாடுகள் மூலம் வழங்குவது) பின்வரும் கூடுதல் தகவல்கள் வழங்கப்பட வேண்டும். ",
					"fundingProportion":"மூல  ஆர்.இ  -இன் பெயர் மற்றும் அது வழங்கும் நிதி விகிதம் ",
					"NameOfThePartner":"கூட்டாளி  ஆர்.இ   பெயர் மற்றும் அது வழங்கும் நிதி விகிதம்",
					"BlendedRateOfInterest":"கலப்பு வட்டி விகிதம்",
			"digitalLoansDisclosures":"டிஜிட்டல் கடன்கள் எனில், பின்வரும் விவரங்கள் வெளியிடப்படும்:",
					"CoolingOffOrlook-upPeriod":"(i) ஆர்.இ  -இன் நிர்வாகக் குழுவினால் ஒப்புதலளிக்கப்பட்ட கொள்கையின்படி கால அவகாசம் (கூலிங் ஆஃப் காலம்) / சிந்திப்பதற்கான கால அவகாசம், இந்த காலத்தில் கடன் தொகையை முன்கூட்டியே செலுத்துவதற்கு எந்தவித அபராத கட்டணமும் விதிக்கப்படாது.  ",
					"DetailsOfLSP":"(ii) மீட்டெடுப்பு முகவராக செயல்படும் மற்றும் கடன் பெறுபவரை அணுக அங்கீகரிக்கப்பட்ட LSP -இன் விவரங்கள்",
		

	"ComputationOfAPR":"ஏபிஆர் கணக்கீடு",

		"Slno":"வரிசை எண்",
		"Parameter":"விவரங்கள்",
		"Details":"விளக்கங்கள்",
			"SanctionedLoanAmount":"ஒப்புதல் அளிக்கப்பட்ட கடன் தொகை (ரூபாயில்)",
			"LoanTerms":"கடன் காலம் (ஆண்டு/மாதம்/நாட்கள்)",
			"NoOfInstalments":"சம அளவிலான காலத் தவணைகளாகப் பிரிக்கப்படாத கடன்களுக்கு அசல் தொகையைச் செலுத்துவதற்கான தவணைகளின் எண்ணிக்கை",
				"instalmentType ":"தவணைகளின் வகை",
				"No of EPIs":"இபிஐ -களின் எண்ணிக்கை",
				"EPIRs":"இபிஐ (ரூ)",
				"Commencementofrepaymentpostsanction":"கடன் வழங்கப்பட்ட பிறகு திரும்பச் செலுத்துதல்",
			"Noofinstalmentsforpayment":"மூலதனமாக்கப்படும் வட்டி எனில் அதனைச் செலுத்துவதற்கான தவணைகளின் எண்ணிக்கை, ஏதாவது இருந்தால், ",
			"Interestratetype":"வட்டி விகித வகை (நிலையானது அல்லது மாறக்கூடியது அல்லது இரண்டும் கலந்தது)",
"Rateofinterest":"வட்டி விகிதம்",			
"Totalinterestamounttobecharged":"கடன் வழங்க ஒப்புதலளிக்கப்பட்ட தினத்தன்று நடைமுறையிலிருந்த வட்டி விகிதத்தின் படி கடன் காலம் முழுவதற்கும் வசூலிக்கப்பட வேண்டிய மொத்த வட்டித் தொகை (ரூபாயில்)",
			"Fee/ChargesPayable":"செலுத்தப்பட வேண்டிய தொகை / கட்டணங்கள்  (ரூபாயில்)",
			"PayabletotheRE":"ஆர்.இ -க்கு செலுத்த வேண்டியது",
			"Payabletothirdparty":"மூன்றாம் நபருக்கு செலுத்தப்பட வேண்டியது",
			"NetDisbursementAmount":"வழங்கப்படும் நிகரத் தொகை  (1-6) (ரூபாயில்)",
			"amountToBePaid":"கடன் பெறுபவரால் செலுத்தப்பட வேண்டிய மொத்தத் தொகை (1 மற்றும் 5 -இன் கூட்டுத் தொகை) (ரூபாயில்)",
			"AnnualPercentagerateInPercent":"வருடாந்திர சதவீதம் – நடைமுறைப்படுத்தப்படும் ஆண்டு வட்டி விகிதல் (சதவீதத்தில்)",
			"ScheduleofDisbursement":"விதிமுறைகள் மற்றும் நிபந்தனைகளின் படியான கடன் வழங்கல் அட்டவணை  ",
			"Duedatepaymentofinstalmentandinterest":"தவணைத் தொகை மற்றும் வட்டி தொகை செலுத்துவதற்கான இறுதி தேதி. ",

			"payableReTypeA":"One Time",
			"payableReTypeB":"One Time",
			"yesOrNo":"Yes",
			"scheduleCondition":"As per repayment Schedule",
			"caglPnoneAndEmail":"Ph:080-22637300, Email: yourvoice@cagrameen.in",


	"Repayment Schedule":"திருப்பிச் செலுத்தும் அட்டவணை",
		"InstalmentNo":"தவணை எண்",
		"OutstandingPrincipal":"அசல் நிலுவைத் தொகை (ரூபாயில்)",
		"Principal":"அசல் தொகை (ரூபாயில்)",
		"Interest":"வட்டி (ரூபாயில்)",
		"Instalment":"தவணை (ரூபாயில்)",
		"Note":""

}
}	 






